remoteauthclient/__init__.py
remoteauthclient/remoteauthclient.py
remoteauthclient-1.4.0.dist-info/LICENSE
remoteauthclient-1.4.0.dist-info/METADATA
remoteauthclient-1.4.0.dist-info/WHEEL
remoteauthclient-1.4.0.dist-info/top_level.txt
remoteauthclient-1.4.0.dist-info/RECORD
