Metadata-Version: 2.1
Name: remoteauthclient
Version: 1.4.0
Summary: Client for Discord authorization via qr code
Home-page: https://github.com/RuslanUC/RemoteAuthClient
Author: RuslanUC
License: MIT
Classifier: Operating System :: OS Independent
Classifier: Programming Language :: Python :: 3.7
Classifier: Programming Language :: Python :: 3.8
Classifier: Programming Language :: Python :: 3.9
Classifier: Programming Language :: Python :: 3.10
Classifier: Programming Language :: Python :: 3.11
Classifier: Programming Language :: Python :: 3.12
Classifier: Topic :: Internet
Classifier: Topic :: Software Development :: Libraries
Classifier: Topic :: Software Development :: Libraries :: Python Modules
Classifier: Topic :: Utilities
Requires-Python: >=3.7
License-File: LICENSE
Requires-Dist: cryptography (>=3.4.7)
Requires-Dist: websockets (>=10.1)
Requires-Dist: aiohttp (>=3.8.1)
